haiku/rag/__init__.py
haiku/rag/app.py
haiku/rag/cli.py
haiku/rag/client.py
haiku/rag/logging.py
haiku/rag/mcp.py
haiku/rag/monitor.py
haiku/rag/utils.py
haiku/rag/agents/__init__.py
haiku/rag/agents/chat/__init__.py
haiku/rag/agents/chat/agent.py
haiku/rag/agents/chat/context.py
haiku/rag/agents/chat/prompts.py
haiku/rag/agents/chat/search.py
haiku/rag/agents/chat/state.py
haiku/rag/agents/qa/__init__.py
haiku/rag/agents/qa/agent.py
haiku/rag/agents/qa/prompts.py
haiku/rag/agents/research/__init__.py
haiku/rag/agents/research/dependencies.py
haiku/rag/agents/research/graph.py
haiku/rag/agents/research/models.py
haiku/rag/agents/research/prompts.py
haiku/rag/agents/research/state.py
haiku/rag/chat/__init__.py
haiku/rag/chat/app.py
haiku/rag/chat/widgets/__init__.py
haiku/rag/chat/widgets/chat_history.py
haiku/rag/chat/widgets/context_modal.py
haiku/rag/chat/widgets/document_filter_modal.py
haiku/rag/chunkers/__init__.py
haiku/rag/chunkers/base.py
haiku/rag/chunkers/docling_local.py
haiku/rag/chunkers/docling_serve.py
haiku/rag/config/__init__.py
haiku/rag/config/loader.py
haiku/rag/config/models.py
haiku/rag/converters/__init__.py
haiku/rag/converters/base.py
haiku/rag/converters/docling_local.py
haiku/rag/converters/docling_serve.py
haiku/rag/converters/text_utils.py
haiku/rag/embeddings/__init__.py
haiku/rag/inspector/__init__.py
haiku/rag/inspector/app.py
haiku/rag/inspector/widgets/__init__.py
haiku/rag/inspector/widgets/chunk_list.py
haiku/rag/inspector/widgets/context_modal.py
haiku/rag/inspector/widgets/detail_view.py
haiku/rag/inspector/widgets/document_list.py
haiku/rag/inspector/widgets/info_modal.py
haiku/rag/inspector/widgets/search_modal.py
haiku/rag/inspector/widgets/visual_modal.py
haiku/rag/providers/__init__.py
haiku/rag/providers/docling_serve.py
haiku/rag/reranking/__init__.py
haiku/rag/reranking/base.py
haiku/rag/reranking/cohere.py
haiku/rag/reranking/jina.py
haiku/rag/reranking/jina_local.py
haiku/rag/reranking/mxbai.py
haiku_rag_slim-0.28.0.dist-info/METADATA
haiku_rag_slim-0.28.0.dist-info/WHEEL
haiku_rag_slim-0.28.0.dist-info/entry_points.txt
haiku_rag_slim-0.28.0.dist-info/licenses/LICENSE
haiku_rag_slim-0.28.0.dist-info/RECORD
