Metadata-Version: 2.4
Name: haiku.rag-slim
Version: 0.28.0
Summary: Opinionated agentic RAG powered by LanceDB, Pydantic AI, and Docling - Minimal dependencies
Author-email: Yiorgis Gozadinos <ggozadinos@gmail.com>
License: MIT
License-File: LICENSE
Keywords: RAG,lancedb,mcp,ml,vector-database
Classifier: Development Status :: 4 - Beta
Classifier: Environment :: Console
Classifier: Intended Audience :: Developers
Classifier: Operating System :: MacOS
Classifier: Operating System :: Microsoft :: Windows :: Windows 10
Classifier: Operating System :: Microsoft :: Windows :: Windows 11
Classifier: Operating System :: POSIX :: Linux
Classifier: Programming Language :: Python :: 3.12
Classifier: Programming Language :: Python :: 3.13
Classifier: Typing :: Typed
Requires-Python: >=3.12
Requires-Dist: docling-core==2.60.1
Requires-Dist: httpx>=0.28.1
Requires-Dist: jsonpatch>=1.33
Requires-Dist: lancedb==0.27.0
Requires-Dist: pathspec>=1.0.3
Requires-Dist: pydantic-ai-slim[ag-ui,fastmcp,logfire,openai]>=1.46.0
Requires-Dist: pydantic>=2.12.5
Requires-Dist: python-dotenv>=1.2.1
Requires-Dist: pyyaml>=6.0.3
Requires-Dist: rich>=14.2.0
Requires-Dist: typer<0.20.0,>=0.19.2
Requires-Dist: watchfiles>=1.1.1
Provides-Extra: anthropic
Requires-Dist: pydantic-ai-slim[anthropic]; extra == 'anthropic'
Provides-Extra: bedrock
Requires-Dist: pydantic-ai-slim[bedrock]; extra == 'bedrock'
Provides-Extra: cohere
Requires-Dist: cohere>=5.20.1; extra == 'cohere'
Provides-Extra: docling
Requires-Dist: docling==2.69.1; extra == 'docling'
Requires-Dist: opencv-python-headless>=4.13.0.90; extra == 'docling'
Provides-Extra: google
Requires-Dist: pydantic-ai-slim[google]; extra == 'google'
Provides-Extra: groq
Requires-Dist: pydantic-ai-slim[groq]; extra == 'groq'
Provides-Extra: jina
Requires-Dist: torch>=2.0.0; extra == 'jina'
Requires-Dist: transformers>=4.40.0; extra == 'jina'
Provides-Extra: mistral
Requires-Dist: pydantic-ai-slim[mistral]; extra == 'mistral'
Provides-Extra: mxbai
Requires-Dist: mxbai-rerank>=0.1.6; extra == 'mxbai'
Provides-Extra: tui
Requires-Dist: textual-image>=0.8.5; extra == 'tui'
Requires-Dist: textual>=7.3.0; extra == 'tui'
Provides-Extra: vertexai
Requires-Dist: pydantic-ai-slim[vertexai]; extra == 'vertexai'
Provides-Extra: voyageai
Requires-Dist: pydantic-ai-slim[voyageai]; extra == 'voyageai'
Provides-Extra: zeroentropy
Requires-Dist: zeroentropy>=0.1.0a7; extra == 'zeroentropy'
